[
  {"size": "большой", "resources": "минимум", "duration": "5 лет"},
  {"size": "средний", "resources": "нормально", "duration": "10 лет"},
  {"size": "маленький", "resources": "ограниченно", "duration": "3 года"},
  {"size": "огромный", "resources": "максимум", "duration": "15 лет"},
  {"size": "подземный", "resources": "нехватка воды", "duration": "2 года"},
  {"size": "автономный", "resources": "полный запас", "duration": "20 лет"},
  {"size": "старый", "resources": "истощены", "duration": "1 год"},
  {"size": "современный", "resources": "возобновляемые источники", "duration": "10 лет"},
  {"size": "военный", "resources": "боеприпасы", "duration": "5 лет"},
  {"size": "космический", "resources": "ограниченный доступ", "duration": "3 года"},
  {"size": "морской", "resources": "рыба и вода", "duration": "7 лет"},
  {"size": "горный", "resources": "минералы", "duration": "15 лет"},
  {"size": "пустынный", "resources": "вода и еда", "duration": "2 года"},
  {"size": "ледяной", "resources": "ограничено", "duration": "1 год"},
  {"size": "в лесу", "resources": "растительность", "duration": "4 года"}
]
